unicloud/__init__.py
unicloud/abstract_class.py
unicloud/aws/__init__.py
unicloud/aws/aws.py
unicloud/google_cloud/__init__.py
unicloud/google_cloud/gcs.py
unicloud/utils.py
unicloud-0.4.0.dist-info/LICENSE.md
unicloud-0.4.0.dist-info/METADATA
unicloud-0.4.0.dist-info/WHEEL
unicloud-0.4.0.dist-info/entry_points.txt
unicloud-0.4.0.dist-info/RECORD
