Metadata-Version: 2.1
Name: unicloud
Version: 0.4.0
Summary: cloud storage utils package
Author: Mostafa Farrag
Author-email: moah.farrag@gmail.com
Requires-Python: >=3.12,<4.0
Classifier: Programming Language :: Python :: 3
Classifier: Programming Language :: Python :: 3.12
Classifier: Programming Language :: Python :: 3.13
Requires-Dist: loguru (>=0.7.2,<0.8.0)
Requires-Dist: numpy (>=2.1.2,<3.0.0)
Requires-Dist: pandas (>=2.2.0,<3.0.0)
